anyskin/__init__.py
anyskin/sensor.py
anyskin/sensor_proc.py
anyskin/visualizations/__init__.py
anyskin/visualizations/anyskin_viz.py
anyskin/visualizations/heatmap.py
anyskin/visualizations/images/viz_bg.png
anyskin-1.0.0.dist-info/LICENSE
anyskin-1.0.0.dist-info/METADATA
anyskin-1.0.0.dist-info/WHEEL
anyskin-1.0.0.dist-info/entry_points.txt
anyskin-1.0.0.dist-info/top_level.txt
anyskin-1.0.0.dist-info/RECORD
