Metadata-Version: 2.1
Name: anyskin
Version: 1.0.0
Summary: Python library for interfacing with an AnySkin sensor
Home-page: https://github.com/raunaqbhirangi/anyskin.git
Author: Raunaq Bhirangi
Author-email: raunaqbhirangi@nyu.edu
Requires-Python: >=3.8
License-File: LICENSE
Requires-Dist: numpy>=1.21.3
Requires-Dist: pyserial>=3.5
Requires-Dist: pygame>=2.6.0
